LICENSE
MANIFEST.in
README.rst
setup.cfg
setup.py
versioneer.py
tpDcc/__init__.py
tpDcc/dccs/__init__.py
tpDcc/dccs/houdini/__init__.py
tpDcc/dccs/houdini/__logging__.ini
tpDcc/dccs/houdini/__version__.py
tpDcc/dccs/houdini/_version.py
tpDcc/dccs/houdini/loader.py
tpDcc/dccs/houdini/core/__init__.py
tpDcc/dccs/houdini/core/dcc.py
tpDcc/dccs/houdini/core/directory.py
tpDcc/dccs/houdini/core/gui.py
tpDcc/dccs/houdini/core/helpers.py
tpDcc/dccs/houdini/core/menu.py
tpDcc/dccs/houdini/core/shelf.py
tpDcc/dccs/houdini/ui/__init__.py
tpDcc/dccs/houdini/ui/dialog.py
tpDcc/dccs/houdini/ui/window.py
tpDcc_dccs_houdini.egg-info/PKG-INFO
tpDcc_dccs_houdini.egg-info/SOURCES.txt
tpDcc_dccs_houdini.egg-info/dependency_links.txt
tpDcc_dccs_houdini.egg-info/not-zip-safe
tpDcc_dccs_houdini.egg-info/requires.txt
tpDcc_dccs_houdini.egg-info/top_level.txt