Metadata-Version: 2.1
Name: tpDcc-dccs-houdini
Version: 0.0.1
Summary: Houdini implementation for tpDcc. Utils functions to work with Houdini Python APIs.
Home-page: https://github.com/tpDcc/tpDcc-dccs-houdini
Author: Tomas Poveda
Author-email: tpovedatd@gmail.com
License: MIT
Platform: UNKNOWN
Provides-Extra: dev
Provides-Extra: test
